CHANGES.rst
LICENSE.txt
MANIFEST.in
README.rst
setup.py
configgen/__init__.py
configgen/config.py
configgen/main.py
configgen/version.py
configgen.egg-info/PKG-INFO
configgen.egg-info/SOURCES.txt
configgen.egg-info/dependency_links.txt
configgen.egg-info/entry_points.txt
configgen.egg-info/top_level.txt