Metadata-Version: 1.1
Name: configgen
Version: 0.1.0
Summary: a noble script configgens the smallest app
Home-page: https://bitbucket.org/dystedium/configgen
Author: wil paredes
Author-email: configgen@dystedium.com
License: UNKNOWN
Platform: UNKNOWN
Classifier: Development Status :: 3 - Alpha
Classifier: Environment :: Console
Classifier: Intended Audience :: Developers
Classifier: Intended Audience :: System Administrators
Classifier: License :: OSI Approved :: MIT License
Classifier: Operating System :: OS Independent
Classifier: Programming Language :: Python :: 2.7
Classifier: Topic :: Software Development :: Code Generators
Classifier: Topic :: Text Processing :: Markup
Classifier: Topic :: Utilities
